spikingtorch/__init__.py
spikingtorch/layers.py
spikingtorch/spikeio.py
spikingtorch/spikingnet.py
spikingtorch-0.1.3.dist-info/LICENSE.md
spikingtorch-0.1.3.dist-info/METADATA
spikingtorch-0.1.3.dist-info/WHEEL
spikingtorch-0.1.3.dist-info/top_level.txt
spikingtorch-0.1.3.dist-info/RECORD
