Metadata-Version: 2.1
Name: spikingtorch
Version: 0.1.3
Summary: Inference and backprop training of spiking neural networks in Pytorch
Author: Angel Yanguas-Gil
Project-URL: Homepage, https://github.com/anglyan/spikingtorch
Keywords: spiking neurons,neural networks,AI,Pytorch,neuromorphic computing,spiking neural networks,neuroscience
Classifier: Programming Language :: Python :: 3
Classifier: License :: OSI Approved :: BSD License
Classifier: Operating System :: OS Independent
License-File: LICENSE.md
Requires-Dist: torch
